google_meridian-1.3.1.dist-info/licenses/LICENSE
meridian/__init__.py
meridian/constants.py
meridian/version.py
meridian/analysis/__init__.py
meridian/analysis/analyzer.py
meridian/analysis/formatter.py
meridian/analysis/optimizer.py
meridian/analysis/summarizer.py
meridian/analysis/summary_text.py
meridian/analysis/test_utils.py
meridian/analysis/visualizer.py
meridian/analysis/review/__init__.py
meridian/analysis/review/checks.py
meridian/analysis/review/configs.py
meridian/analysis/review/constants.py
meridian/analysis/review/results.py
meridian/analysis/review/reviewer.py
meridian/analysis/templates/card.html.jinja
meridian/analysis/templates/chart.html.jinja
meridian/analysis/templates/chips.html.jinja
meridian/analysis/templates/insights.html.jinja
meridian/analysis/templates/stats.html.jinja
meridian/analysis/templates/style.css
meridian/analysis/templates/style.scss
meridian/analysis/templates/summary.html.jinja
meridian/analysis/templates/table.html.jinja
meridian/backend/__init__.py
meridian/backend/config.py
meridian/backend/test_utils.py
meridian/data/__init__.py
meridian/data/arg_builder.py
meridian/data/data_frame_input_data_builder.py
meridian/data/input_data.py
meridian/data/input_data_builder.py
meridian/data/load.py
meridian/data/nd_array_input_data_builder.py
meridian/data/test_utils.py
meridian/data/time_coordinates.py
meridian/mlflow/__init__.py
meridian/mlflow/autolog.py
meridian/model/__init__.py
meridian/model/adstock_hill.py
meridian/model/knots.py
meridian/model/media.py
meridian/model/model.py
meridian/model/model_test_data.py
meridian/model/posterior_sampler.py
meridian/model/prior_distribution.py
meridian/model/prior_sampler.py
meridian/model/spec.py
meridian/model/transformers.py
meridian/model/eda/__init__.py
meridian/model/eda/constants.py
meridian/model/eda/eda_engine.py
meridian/model/eda/eda_outcome.py
meridian/model/eda/eda_spec.py
meridian/model/eda/meridian_eda.py
schema/__init__.py
schema/serde/__init__.py
schema/serde/constants.py
schema/serde/distribution.py
google_meridian-1.3.1.dist-info/METADATA
google_meridian-1.3.1.dist-info/WHEEL
google_meridian-1.3.1.dist-info/top_level.txt
google_meridian-1.3.1.dist-info/RECORD
