Metadata-Version: 2.4
Name: google-meridian
Version: 1.3.1
Summary: Google's open source mixed marketing model library, helps you understand your return on investment and direct your ad spend with confidence. 
Author-email: The Meridian Authors <no-reply@google.com>
Project-URL: homepage, https://github.com/google/meridian
Project-URL: repository, https://github.com/google/meridian
Project-URL: changelog, https://github.com/google/meridian/blob/main/CHANGELOG.md
Project-URL: documentation, https://developers.google.com/meridian
Keywords: mmm
Classifier: Programming Language :: Python :: 3
Classifier: Programming Language :: Python :: 3 :: Only
Classifier: Topic :: Other/Nonlisted Topic
Classifier: Topic :: Scientific/Engineering :: Information Analysis
Requires-Python: >=3.10
License-File: LICENSE
Requires-Dist: arviz
Requires-Dist: altair>=5
Requires-Dist: immutabledict
Requires-Dist: joblib
Requires-Dist: natsort<8,>=7.1.1
Requires-Dist: numpy<3,>=2.0.2
Requires-Dist: pandas<3,>=2.2.2
Requires-Dist: patsy<1,>=0.5.3
Requires-Dist: scipy<2,>=1.13.1
Requires-Dist: statsmodels>=0.14.5
Requires-Dist: tensorflow<2.19,>=2.18
Requires-Dist: tensorflow-probability<0.26,>=0.25
Requires-Dist: tf-keras<2.19,>=2.18
Requires-Dist: xarray
Provides-Extra: dev
Requires-Dist: pytest>=8.0.0; extra == "dev"
Requires-Dist: pytest-xdist; extra == "dev"
Requires-Dist: pylint>=2.6.0; extra == "dev"
Requires-Dist: pyink; extra == "dev"
Provides-Extra: colab
Requires-Dist: psutil; extra == "colab"
Requires-Dist: python-calamine; extra == "colab"
Provides-Extra: and-cuda
Requires-Dist: tensorflow[and-cuda]<2.19,>=2.18; extra == "and-cuda"
Provides-Extra: mlflow
Requires-Dist: mlflow; extra == "mlflow"
Provides-Extra: jax
Requires-Dist: jax==0.4.26; extra == "jax"
Requires-Dist: jaxlib==0.4.26; extra == "jax"
Requires-Dist: tensorflow-probability[substrates-jax]==0.25.0; extra == "jax"
Provides-Extra: schema
Requires-Dist: mmm-proto-schema; extra == "schema"
Requires-Dist: semver; extra == "schema"
Dynamic: license-file
